{
  "0": "0",
  "1": "2W",
  "2": "2WB",
  "3": "5B",
  "4": "5F",
  "5": "7B",
  "6": "7F",
  "7": "B",
  "8": "BB",
  "9": "BFL",
  "10": "BFLB",
  "11": "BFLF",
  "12": "END",
  "13": "F",
  "14": "FALL",
  "15": "FFL",
  "16": "FFLO",
  "17": "LB",
  "18": "LF",
  "19": "O",
  "20": "OB",
  "21": "R2W",
  "22": "R2WB",
  "23": "R5B",
  "24": "R5F",
  "25": "R7B",
  "26": "R7F",
  "27": "RB",
  "28": "RBB",
  "29": "RBFL",
  "30": "RF",
  "31": "RO",
  "32": "ROB",
  "33": "RS",
  "34": "RSLB",
  "35": "RTB",
  "36": "RTBB",
  "37": "RTF",
  "38": "RTO",
  "39": "RTOB",
  "40": "RTS",
  "41": "RTWB",
  "42": "RTWBB",
  "43": "RTWO",
  "44": "RW5F",
  "45": "RW7B",
  "46": "RWB",
  "47": "RWBB",
  "48": "RWF",
  "49": "RWO",
  "50": "RWOB",
  "51": "S",
  "52": "SLB",
  "53": "SLBB",
  "54": "SLOB",
  "55": "T5B",
  "56": "T5F",
  "57": "T7",
  "58": "T7F",
  "59": "TB",
  "60": "TBB",
  "61": "TF",
  "62": "TO",
  "63": "TOB",
  "64": "TS",
  "65": "TWB",
  "66": "TWBB",
  "67": "TWF",
  "68": "TWLB",
  "69": "TWLO",
  "70": "TWO",
  "71": "TWOB",
  "72": "W5B",
  "73": "W5F",
  "74": "W7B",
  "75": "WB",
  "76": "WBB",
  "77": "WF",
  "78": "WL5F",
  "79": "WLB",
  "80": "WLF",
  "81": "WLO",
  "82": "WO",
  "83": "WOB",
  "84": "b",
  "85": "bb",
  "86": "f",
  "87": "lb",
  "88": "o",
  "89": "r7F",
  "90": "rO",
  "91": "rWF",
  "92": "ro",
  "93": "rs",
  "94": "s"
}