{
  "0": "5B",
  "1": "5F",
  "2": "7B",
  "3": "7F",
  "4": "B",
  "5": "BB",
  "6": "BFL",
  "7": "BFLB",
  "8": "BFLBB",
  "9": "BFLF",
  "10": "END",
  "11": "F",
  "12": "FALL",
  "13": "FFL",
  "14": "FFLF",
  "15": "LB",
  "16": "LF",
  "17": "O",
  "18": "OB",
  "19": "R5B",
  "20": "R5F",
  "21": "R7B",
  "22": "R7F",
  "23": "RB",
  "24": "RBB",
  "25": "RBFL",
  "26": "RBFLB",
  "27": "RBFLBB",
  "28": "RF",
  "29": "RFFL",
  "30": "RO",
  "31": "ROB",
  "32": "RS",
  "33": "RT5B",
  "34": "RTB",
  "35": "RTBB",
  "36": "RTF",
  "37": "RTO",
  "38": "RTS",
  "39": "RTWB",
  "40": "RTWBB",
  "41": "RTWLBB",
  "42": "RW5F",
  "43": "RWB",
  "44": "RWBB",
  "45": "RWF",
  "46": "RWO",
  "47": "S",
  "48": "SL5F",
  "49": "SLB",
  "50": "SLBB",
  "51": "SLO",
  "52": "T5B",
  "53": "T5F",
  "54": "T7F",
  "55": "TB",
  "56": "TBB",
  "57": "TF",
  "58": "TO",
  "59": "TS",
  "60": "TW5B",
  "61": "TWB",
  "62": "TWBB",
  "63": "TWF",
  "64": "TWLB",
  "65": "TWLBB",
  "66": "TWLF",
  "67": "TWLO",
  "68": "TWO",
  "69": "W5B",
  "70": "W5F",
  "71": "WB",
  "72": "WBB",
  "73": "WF",
  "74": "WLB",
  "75": "WLF",
  "76": "WLO",
  "77": "WO"
}